ipydrawio_mathjax/__init__.py
ipydrawio_mathjax/_version.py
ipydrawio_mathjax/etc/install.json
ipydrawio_mathjax-1.3.0.data/data/share/jupyter/labextensions/@deathbeds/ipydrawio-mathjax/install.json
ipydrawio_mathjax-1.3.0.data/data/share/jupyter/labextensions/@deathbeds/ipydrawio-mathjax/package.json
ipydrawio_mathjax-1.3.0.data/data/share/jupyter/labextensions/@deathbeds/ipydrawio-mathjax/static/480.4e5821ae6810e33f4c3b.js
ipydrawio_mathjax-1.3.0.data/data/share/jupyter/labextensions/@deathbeds/ipydrawio-mathjax/static/568.6474bf67e268a15a4277.js
ipydrawio_mathjax-1.3.0.data/data/share/jupyter/labextensions/@deathbeds/ipydrawio-mathjax/static/remoteEntry.6abe8eb6564d5e102902.js
ipydrawio_mathjax-1.3.0.data/data/share/jupyter/labextensions/@deathbeds/ipydrawio-mathjax/static/style.js
ipydrawio_mathjax-1.3.0.data/data/share/jupyter/labextensions/@deathbeds/ipydrawio-mathjax/static/third-party-licenses.json
ipydrawio_mathjax-1.3.0.data/data/share/jupyter/labextensions/@deathbeds/ipydrawio-mathjax/static/dio/math/package.json
ipydrawio_mathjax-1.3.0.data/data/share/jupyter/labextensions/@deathbeds/ipydrawio-mathjax/static/dio/math/es5/core.js
ipydrawio_mathjax-1.3.0.data/data/share/jupyter/labextensions/@deathbeds/ipydrawio-mathjax/static/dio/math/es5/latest.js
ipydrawio_mathjax-1.3.0.data/data/share/jupyter/labextensions/@deathbeds/ipydrawio-mathjax/static/dio/math/es5/loader.js
ipydrawio_mathjax-1.3.0.data/data/share/jupyter/labextensions/@deathbeds/ipydrawio-mathjax/static/dio/math/es5/mml-chtml.js
ipydrawio_mathjax-1.3.0.data/data/share/jupyter/labextensions/@deathbeds/ipydrawio-mathjax/static/dio/math/es5/mml-svg.js
ipydrawio_mathjax-1.3.0.data/data/share/jupyter/labextensions/@deathbeds/ipydrawio-mathjax/static/dio/math/es5/node-main.js
ipydrawio_mathjax-1.3.0.data/data/share/jupyter/labextensions/@deathbeds/ipydrawio-mathjax/static/dio/math/es5/startup.js
ipydrawio_mathjax-1.3.0.dist-info/LICENSE.txt
ipydrawio_mathjax-1.3.0.dist-info/METADATA
ipydrawio_mathjax-1.3.0.dist-info/WHEEL
ipydrawio_mathjax-1.3.0.dist-info/top_level.txt
ipydrawio_mathjax-1.3.0.dist-info/RECORD
