Metadata-Version: 2.1
Name: ipydrawio-mathjax
Version: 1.3.0
Summary: MathJax for ipydrawio
Home-page: https://ipydrawio.rtfd.io
Author: ipydrawio Contributors
Author-email: ripxl@example.com
License: Apache-2.0
Project-URL: Bug Tracker, https://github.com/deathbeds/ipydrawio/issues
Project-URL: Changelog, https://github.com/deathbeds/ipydrawio/blob/main/CHANGELOG.md
Project-URL: Coverage, https://app.codecov.io/gh/deathbeds/ipydrawio
Project-URL: Documentation, https://ipydrawio.rtfd.io
Project-URL: Source Code, https://github.com/deathbeds/ipydrawio
Classifier: Development Status :: 4 - Beta
Classifier: Framework :: Jupyter
Classifier: Framework :: Jupyter :: JupyterLab :: 3
Classifier: Framework :: Jupyter :: JupyterLab :: Extensions
Classifier: Framework :: Jupyter :: JupyterLab :: Extensions :: Prebuilt
Classifier: Intended Audience :: Developers
Classifier: Intended Audience :: Information Technology
Classifier: License :: OSI Approved :: Apache Software License
Classifier: Programming Language :: Python
Classifier: Programming Language :: Python :: 3 :: Only
Classifier: Programming Language :: Python :: 3.8
Classifier: Programming Language :: Python :: 3.9
Classifier: Programming Language :: Python :: 3.10
Classifier: Programming Language :: Python :: 3.11
Classifier: Topic :: Multimedia :: Graphics :: Editors :: Vector-Based
Classifier: Topic :: Multimedia :: Graphics :: Presentation
Requires-Python: >=3.8
License-File: LICENSE.txt
Requires-Dist: ipydrawio (==1.3.0)
Provides-Extra: test
Requires-Dist: pytest ; extra == 'test'
